sentry_sdk_scrapy/__init__.py
sentry_sdk_scrapy/extensions.py
sentry_sdk_scrapy-0.4.1.dist-info/WHEEL
sentry_sdk_scrapy-0.4.1.dist-info/METADATA
sentry_sdk_scrapy-0.4.1.dist-info/RECORD
