Metadata-Version: 2.1
Name: sentry-sdk-scrapy
Version: 0.4.1
Summary: Scrapy extension for integration of Sentry SDK to Scrapy projects
Home-page: https://github.com/nouseforacode/scrapy-sentry-sdk/
License: MIT
Keywords: Error reporting,Monitoring,Scrapy,Sentry
Author: KristobalJunta
Author-email: junta.kristobal@gmail.com
Requires-Python: >=3.6
Classifier: License :: OSI Approved :: MIT License
Classifier: Programming Language :: Python :: 3
Classifier: Programming Language :: Python :: 3.6
Classifier: Programming Language :: Python :: 3.7
Classifier: Programming Language :: Python :: 3.8
Classifier: Programming Language :: Python :: 3.9
Classifier: Topic :: Software Development :: Libraries :: Python Modules
Requires-Dist: Scrapy (>=2.4.1,<3.0.0)
Requires-Dist: sentry-sdk (>=0.19.4,<0.20.0)
Project-URL: Repository, https://github.com/nouseforacode/scrapy-sentry-sdk/
